arikedb/__init__.py
arikedb/arike_auth_pb2.py
arikedb/arike_collection_pb2.py
arikedb/arike_fifo_pb2.py
arikedb/arike_main_pb2.py
arikedb/arike_main_pb2_grpc.py
arikedb/arike_sorted_list_pb2.py
arikedb/arike_stack_pb2.py
arikedb/arike_ts_variable_pb2.py
arikedb/arike_utils_pb2.py
arikedb/arikedb.py
arikedb/common.py
arikedb-1.1.3.dist-info/LICENSE
arikedb-1.1.3.dist-info/METADATA
arikedb-1.1.3.dist-info/WHEEL
arikedb-1.1.3.dist-info/top_level.txt
arikedb-1.1.3.dist-info/RECORD
