Metadata-Version: 2.1
Name: arikedb
Version: 1.1.3
Summary: ArikeDB Python Client Library
Home-page: https://github.com/Arikedb/arikedb-python
Author: Alejandro Alfonso
Author-email: alejandroalfonso1994@gmail.com
License: MIT
License-File: LICENSE
Requires-Dist: grpcio>=1.65.0
Requires-Dist: protobuf>=5.27.0
